fifo/mem.v
module mem(      input                      wr,
                 input      [7:0]           DB,
				 input      [8:0]           in_adr,
                 input      [8:0]           out_adr,
                 input                      out_en,                       
				 input                      Clk,
				 input		                Rst,
                 input                      bit4,
                 output      [2:0]          out);
			  
			     reg        [511:0]          mem    ;
			    

         integer i; 
             always@                   (negedge Clk)
			            begin
			                  if          (Rst == 0)

					
			                           for(i = 0; i == 511; i = i+1) 
          
			                               mem [i]= 0;

			  
			                  else
                               if     (wr == 0)
                               if     (!bit4)
							        begin
                                       mem [in_adr] <= DB [0];
                                       mem [in_adr+1] <= DB [1];
									   mem [in_adr+2] <= DB [2];
									   mem [in_adr+3] <= DB [3];
									   mem [in_adr+4] <= DB [4];
									   mem [in_adr+5] <= DB [5];
									   mem [in_adr+6] <= DB [6];
									   mem [in_adr+7] <= DB [7];
								    end	   
                                else   
								    begin
								       mem [in_adr] <= DB [0];
                                       mem [in_adr+1] <= DB [1];
									   mem [in_adr+2] <= DB [2];
									   mem [in_adr+3] <= DB [3];
									end
						end

           reg     out0,out1,out2;

           always@      (out_en or out_adr)
			  begin
                  if(out_en)
				  begin
					  
			                     out0 <= mem [out_adr] ;
								 out1 <= mem [out_adr+1];
								 out2 <= mem [out_adr+2];
				  end
			  end
		   assign out= {out2, out1, out0};
 
endmodule

fifo/control.v
module control(input                              Clk,
               input                              Rst,
               input                              bit4,
               input                              wr,
               output               reg           out_en,
               output               wire          overflow,
               output               reg   [8:0]   out_adr=9'b000000000,
               output               reg   [8:0]   in_adr=9'b000000000); 

reg            overflow1            =             0;
assign         overflow             =             overflow1;
 

always                              @             (posedge Clk)
    begin
        if                                            (!wr) 
            begin
                if(!bit4)
                in_adr              =              in_adr+8;
            else
                in_adr              =              in_adr+4;    
            end 
    end

always                              @             (posedge Clk)
    if                                            (out_en) 
    begin
        out_adr=out_adr+3;    
    end

always                              @             (posedge Clk)
    begin
        if (in_adr>out_adr+384 || (in_adr<out_adr && out_adr<in_adr+96)) 
        overflow1                   =               1;  
        else
        overflow1                   =               0;
    end
always                              @              (posedge Clk)
        begin
            if                                     (in_adr>out_adr+128)
            out_en                  =               1;
        end
endmodule

fifo/top.v
module top(input Clk,
           input Rst,
           input bit4,
           input [7:0] DB,
           input wr,
           output overflow,
           output  wire [2:0] out);

           wire     out_en;
           wire     [8:0] out_adr,in_adr;

           control control1(.Clk(Clk),
                            .wr(wr),
                            .Rst(Rst),
                            .bit4(bit4),
                            .out_en(out_en),
                            .overflow(overflow),
                            .out_adr(out_adr),
                            .in_adr(in_adr));
           mem mem1(.DB(DB),
                    .wr(wr),
                    .in_adr(in_adr),
                    .out_adr(out_adr),
                    .out_en(out_en),
                    .Clk(Clk),
                    .Rst(Rst),
                    .bit4(bit4),
                    .out(out));
endmodule

fifo/tb_fifo.v
`timescale 1ns/1ps 
module tb_fifo();


    reg Clk;

        initial 
        begin
            Clk = 1'b1;
        forever #(5) Clk = ~Clk;
        end

    reg Rst;

        initial begin
            Rst <= 1'b0;
            #1
            Rst <= 1'b1;
        end

    reg bit4;
        initial 
        begin
            bit4        =              0;
            #6440
            bit4        =              1;
        end

    reg               [7:0]            DB;
    wire              [2:0]            out;
    wire overflow;
    reg wr;

    top top1(.Clk                     (Clk),
             .Rst                     (Rst),
             .bit4                    (bit4),
             .DB                      (DB),
             .wr                      (wr),
             .overflow                (overflow),
             .out                     (out));
              integer id;

        initial begin 
            DB          <=             0;
            #4
            wr          <=             0;
            DB          <=             1;
           
            for (id = 1; id < 64; id = id + 1)
                begin
                    #10
                    DB  <=             id+1;
                end
            #10 DB <=0;
            for (id = 1; id < 64; id = id + 1)
                begin
                    #10
                    DB  <=             id+1;
                end
            
            repeat(175)@(posedge Clk);
            $finish;
        end

    initial
    	begin
      		$dumpfile("wave.vcd");
            $dumpvars(0, tb_fifo);
    	end
endmodule

fifo/wave.vcd
$date
	Thu Dec  3 22:31:22 2020
$end
$version
	Icarus Verilog
$end
$timescale
	1ps
$end
$scope module tb_fifo $end
$var wire 1 ! overflow $end
$var wire 3 " out [2:0] $end
$var reg 1 # Clk $end
$var reg 8 $ DB [7:0] $end
$var reg 1 % Rst $end
$var reg 1 & bit4 $end
$var reg 1 ' wr $end
$var integer 32 ( id [31:0] $end
$scope module top1 $end
$var wire 1 # Clk $end
$var wire 8 ) DB [7:0] $end
$var wire 1 % Rst $end
$var wire 1 & bit4 $end
$var wire 1 ' wr $end
$var wire 1 ! overflow $end
$var wire 1 * out_en $end
$var wire 9 + out_adr [8:0] $end
$var wire 3 , out [2:0] $end
$var wire 9 - in_adr [8:0] $end
$scope module control1 $end
$var wire 1 # Clk $end
$var wire 1 % Rst $end
$var wire 1 & bit4 $end
$var wire 1 ! overflow $end
$var wire 1 ' wr $end
$var reg 9 . in_adr [8:0] $end
$var reg 9 / out_adr [8:0] $end
$var reg 1 * out_en $end
$var reg 1 0 overflow1 $end
$upscope $end
$scope module mem1 $end
$var wire 1 # Clk $end
$var wire 8 1 DB [7:0] $end
$var wire 1 % Rst $end
$var wire 1 & bit4 $end
$var wire 9 2 in_adr [8:0] $end
$var wire 9 3 out_adr [8:0] $end
$var wire 1 * out_en $end
$var wire 1 ' wr $end
$var wire 3 4 out [2:0] $end
$var reg 512 5 mem [511:0] $end
$var reg 1 6 out0 $end
$var reg 1 7 out1 $end
$var reg 1 8 out2 $end
$var integer 32 9 i [31:0] $end
$upscope $end
$upscope $end
$upscope $end
$enddefinitions $end
#0
$dumpvars
bx 9
x8
x7
x6
bx 5
bx 4
b0 3
b0 2
b0 1
00
b0 /
b0 .
b0 -
bx ,
b0 +
x*
b0 )
bx (
x'
0&
0%
b0 $
1#
bx "
0!
$end
#1000
1%
#4000
b1 $
b1 )
b1 1
0'
b1 (
#5000
bx00000001 5
0#
#10000
b1000 -
b1000 .
b1000 2
1#
#14000
b10 $
b10 )
b10 1
b10 (
#15000
bx0000001000000001 5
0#
#20000
b10000 -
b10000 .
b10000 2
1#
#24000
b11 $
b11 )
b11 1
b11 (
#25000
bx000000110000001000000001 5
0#
#30000
b11000 -
b11000 .
b11000 2
1#
#34000
b100 $
b100 )
b100 1
b100 (
#35000
bx00000100000000110000001000000001 5
0#
#40000
b100000 -
b100000 .
b100000 2
1#
#44000
b101 $
b101 )
b101 1
b101 (
#45000
bx0000010100000100000000110000001000000001 5
0#
#50000
b101000 -
b101000 .
b101000 2
1#
#54000
b110 $
b110 )
b110 1
b110 (
#55000
bx000001100000010100000100000000110000001000000001 5
0#
#60000
b110000 -
b110000 .
b110000 2
1#
#64000
b111 $
b111 )
b111 1
b111 (
#65000
bx00000111000001100000010100000100000000110000001000000001 5
0#
#70000
b111000 -
b111000 .
b111000 2
1#
#74000
b1000 $
b1000 )
b1000 1
b1000 (
#75000
bx0000100000000111000001100000010100000100000000110000001000000001 5
0#
#80000
b1000000 -
b1000000 .
b1000000 2
1#
#84000
b1001 $
b1001 )
b1001 1
b1001 (
#85000
bx000010010000100000000111000001100000010100000100000000110000001000000001 5
0#
#90000
b1001000 -
b1001000 .
b1001000 2
1#
#94000
b1010 $
b1010 )
b1010 1
b1010 (
#95000
bx00001010000010010000100000000111000001100000010100000100000000110000001000000001 5
0#
#100000
b1010000 -
b1010000 .
b1010000 2
1#
#104000
b1011 $
b1011 )
b1011 1
b1011 (
#105000
bx0000101100001010000010010000100000000111000001100000010100000100000000110000001000000001 5
0#
#110000
b1011000 -
b1011000 .
b1011000 2
1#
#114000
b1100 $
b1100 )
b1100 1
b1100 (
#115000
bx000011000000101100001010000010010000100000000111000001100000010100000100000000110000001000000001 5
0#
#120000
b1100000 -
b1100000 .
b1100000 2
1#
#124000
b1101 $
b1101 )
b1101 1
b1101 (
#125000
bx00001101000011000000101100001010000010010000100000000111000001100000010100000100000000110000001000000001 5
0#
#130000
b1101000 -
b1101000 .
b1101000 2
1#
#134000
b1110 $
b1110 )
b1110 1
b1110 (
#135000
bx0000111000001101000011000000101100001010000010010000100000000111000001100000010100000100000000110000001000000001 5
0#
#140000
b1110000 -
b1110000 .
b1110000 2
1#
#144000
b1111 $
b1111 )
b1111 1
b1111 (
#145000
bx000011110000111000001101000011000000101100001010000010010000100000000111000001100000010100000100000000110000001000000001 5
0#
#150000
b1111000 -
b1111000 .
b1111000 2
1#
#154000
b10000 $
b10000 )
b10000 1
b10000 (
#155000
bx00010000000011110000111000001101000011000000101100001010000010010000100000000111000001100000010100000100000000110000001000000001 5
0#
#160000
b10000000 -
b10000000 .
b10000000 2
1#
#164000
b10001 $
b10001 )
b10001 1
b10001 (
#165000
bx0001000100010000000011110000111000001101000011000000101100001010000010010000100000000111000001100000010100000100000000110000001000000001 5
0#
#170000
08
07
b1 "
b1 ,
b1 4
16
1*
b10001000 -
b10001000 .
b10001000 2
1#
#174000
b10010 $
b10010 )
b10010 1
b10010 (
#175000
bx000100100001000100010000000011110000111000001101000011000000101100001010000010010000100000000111000001100000010100000100000000110000001000000001 5
0#
#180000
b0 "
b0 ,
b0 4
06
b10010000 -
b10010000 .
b10010000 2
b11 +
b11 /
b11 3
1#
#184000
b10011 $
b10011 )
b10011 1
b10011 (
#185000
bx00010011000100100001000100010000000011110000111000001101000011000000101100001010000010010000100000000111000001100000010100000100000000110000001000000001 5
0#
#190000
b110 +
b110 /
b110 3
b10011000 -
b10011000 .
b10011000 2
1#
#194000
b10100 $
b10100 )
b10100 1
b10100 (
#195000
bx0001010000010011000100100001000100010000000011110000111000001101000011000000101100001010000010010000100000000111000001100000010100000100000000110000001000000001 5
0#
#200000
b1 "
b1 ,
b1 4
16
b10100000 -
b10100000 .
b10100000 2
b1001 +
b1001 /
b1001 3
1#
#204000
b10101 $
b10101 )
b10101 1
b10101 (
#205000
bx000101010001010000010011000100100001000100010000000011110000111000001101000011000000101100001010000010010000100000000111000001100000010100000100000000110000001000000001 5
0#
#210000
b0 "
b0 ,
b0 4
06
b1100 +
b1100 /
b1100 3
b10101000 -
b10101000 .
b10101000 2
1#
#214000
b10110 $
b10110 )
b10110 1
b10110 (
#215000
bx00010110000101010001010000010011000100100001000100010000000011110000111000001101000011000000101100001010000010010000100000000111000001100000010100000100000000110000001000000001 5
0#
#220000
18
b110 "
b110 ,
b110 4
17
b10110000 -
b10110000 .
b10110000 2
b1111 +
b1111 /
b1111 3
1#
#224000
b10111 $
b10111 )
b10111 1
b10111 (
#225000
bx0001011100010110000101010001010000010011000100100001000100010000000011110000111000001101000011000000101100001010000010010000100000000111000001100000010100000100000000110000001000000001 5
0#
#230000
08
b0 "
b0 ,
b0 4
07
b10010 +
b10010 /
b10010 3
b10111000 -
b10111000 .
b10111000 2
1#
#234000
b11000 $
b11000 )
b11000 1
b11000 (
#235000
bx000110000001011100010110000101010001010000010011000100100001000100010000000011110000111000001101000011000000101100001010000010010000100000000111000001100000010100000100000000110000001000000001 5
0#
#240000
b11000000 -
b11000000 .
b11000000 2
b10101 +
b10101 /
b10101 3
1#
#244000
b11001 $
b11001 )
b11001 1
b11001 (
#245000
bx00011001000110000001011100010110000101010001010000010011000100100001000100010000000011110000111000001101000011000000101100001010000010010000100000000111000001100000010100000100000000110000001000000001 5
0#
#250000
b100 "
b100 ,
b100 4
18
b11000 +
b11000 /
b11000 3
b11001000 -
b11001000 .
b11001000 2
1#
#254000
b11010 $
b11010 )
b11010 1
b11010 (
#255000
bx0001101000011001000110000001011100010110000101010001010000010011000100100001000100010000000011110000111000001101000011000000101100001010000010010000100000000111000001100000010100000100000000110000001000000001 5
0#
#260000
b0 "
b0 ,
b0 4
08
b11010000 -
b11010000 .
b11010000 2
b11011 +
b11011 /
b11011 3
1#
#264000
b11011 $
b11011 )
b11011 1
b11011 (
#265000
bx000110110001101000011001000110000001011100010110000101010001010000010011000100100001000100010000000011110000111000001101000011000000101100001010000010010000100000000111000001100000010100000100000000110000001000000001 5
0#
#270000
b100 "
b100 ,
b100 4
18
b11110 +
b11110 /
b11110 3
b11011000 -
b11011000 .
b11011000 2
1#
#274000
b11100 $
b11100 )
b11100 1
b11100 (
#275000
bx00011100000110110001101000011001000110000001011100010110000101010001010000010011000100100001000100010000000011110000111000001101000011000000101100001010000010010000100000000111000001100000010100000100000000110000001000000001 5
0#
#280000
08
b10 "
b10 ,
b10 4
17
b11100000 -
b11100000 .
b11100000 2
b100001 +
b100001 /
b100001 3
1#
#284000
b11101 $
b11101 )
b11101 1
b11101 (
#285000
bx0001110100011100000110110001101000011001000110000001011100010110000101010001010000010011000100100001000100010000000011110000111000001101000011000000101100001010000010010000100000000111000001100000010100000100000000110000001000000001 5
0#
#290000
b0 "
b0 ,
b0 4
07
b100100 +
b100100 /
b100100 3
b11101000 -
b11101000 .
b11101000 2
1#
#294000
b11110 $
b11110 )
b11110 1
b11110 (
#295000
bx000111100001110100011100000110110001101000011001000110000001011100010110000101010001010000010011000100100001000100010000000011110000111000001101000011000000101100001010000010010000100000000111000001100000010100000100000000110000001000000001 5
0#
#300000
b100 "
b100 ,
b100 4
18
b11110000 -
b11110000 .
b11110000 2
b100111 +
b100111 /
b100111 3
1#
#304000
b11111 $
b11111 )
b11111 1
b11111 (
#305000
bx00011111000111100001110100011100000110110001101000011001000110000001011100010110000101010001010000010011000100100001000100010000000011110000111000001101000011000000101100001010000010010000100000000111000001100000010100000100000000110000001000000001 5
0#
#310000
08
b1 "
b1 ,
b1 4
16
b101010 +
b101010 /
b101010 3
b11111000 -
b11111000 .
b11111000 2
1#
#314000
b100000 $
b100000 )
b100000 1
b100000 (
#315000
bx0010000000011111000111100001110100011100000110110001101000011001000110000001011100010110000101010001010000010011000100100001000100010000000011110000111000001101000011000000101100001010000010010000100000000111000001100000010100000100000000110000001000000001 5
0#
#320000
b0 "
b0 ,
b0 4
06
b100000000 -
b100000000 .
b100000000 2
b101101 +
b101101 /
b101101 3
1#
#324000
b100001 $
b100001 )
b100001 1
b100001 (
#325000
bx001000010010000000011111000111100001110100011100000110110001101000011001000110000001011100010110000101010001010000010011000100100001000100010000000011110000111000001101000011000000101100001010000010010000100000000111000001100000010100000100000000110000001000000001 5
0#
#330000
18
17
b111 "
b111 ,
b111 4
16
b110000 +
b110000 /
b110000 3
b100001000 -
b100001000 .
b100001000 2
1#
#334000
b100010 $
b100010 )
b100010 1
b100010 (
#335000
bx00100010001000010010000000011111000111100001110100011100000110110001101000011001000110000001011100010110000101010001010000010011000100100001000100010000000011110000111000001101000011000000101100001010000010010000100000000111000001100000010100000100000000110000001000000001 5
0#
#340000
08
07
b0 "
b0 ,
b0 4
06
b100010000 -
b100010000 .
b100010000 2
b110011 +
b110011 /
b110011 3
1#
#344000
b100011 $
b100011 )
b100011 1
b100011 (
#345000
bx0010001100100010001000010010000000011111000111100001110100011100000110110001101000011001000110000001011100010110000101010001010000010011000100100001000100010000000011110000111000001101000011000000101100001010000010010000100000000111000001100000010100000100000000110000001000000001 5
0#
#350000
b110110 +
b110110 /
b110110 3
b100011000 -
b100011000 .
b100011000 2
1#
#354000
b100100 $
b100100 )
b100100 1
b100100 (
#355000
bx001001000010001100100010001000010010000000011111000111100001110100011100000110110001101000011001000110000001011100010110000101010001010000010011000100100001000100010000000011110000111000001101000011000000101100001010000010010000100000000111000001100000010100000100000000110000001000000001 5
0#
#360000
b100 "
b100 ,
b100 4
18
b100100000 -
b100100000 .
b100100000 2
b111001 +
b111001 /
b111001 3
1#
#364000
b100101 $
b100101 )
b100101 1
b100101 (
#365000
bx00100101001001000010001100100010001000010010000000011111000111100001110100011100000110110001101000011001000110000001011100010110000101010001010000010011000100100001000100010000000011110000111000001101000011000000101100001010000010010000100000000111000001100000010100000100000000110000001000000001 5
0#
#370000
b0 "
b0 ,
b0 4
08
b111100 +
b111100 /
b111100 3
b100101000 -
b100101000 .
b100101000 2
1#
#374000
b100110 $
b100110 )
b100110 1
b100110 (
#375000
bx0010011000100101001001000010001100100010001000010010000000011111000111100001110100011100000110110001101000011001000110000001011100010110000101010001010000010011000100100001000100010000000011110000111000001101000011000000101100001010000010010000100000000111000001100000010100000100000000110000001000000001 5
0#
#380000
b10 "
b10 ,
b10 4
17
b100110000 -
b100110000 .
b100110000 2
b111111 +
b111111 /
b111111 3
1#
#384000
b100111 $
b100111 )
b100111 1
b100111 (
#385000
bx001001110010011000100101001001000010001100100010001000010010000000011111000111100001110100011100000110110001101000011001000110000001011100010110000101010001010000010011000100100001000100010000000011110000111000001101000011000000101100001010000010010000100000000111000001100000010100000100000000110000001000000001 5
0#
#390000
b1000010 +
b1000010 /
b1000010 3
b100111000 -
b100111000 .
b100111000 2
1#
#394000
b101000 $
b101000 )
b101000 1
b101000 (
#395000
bx00101000001001110010011000100101001001000010001100100010001000010010000000011111000111100001110100011100000110110001101000011001000110000001011100010110000101010001010000010011000100100001000100010000000011110000111000001101000011000000101100001010000010010000100000000111000001100000010100000100000000110000001000000001 5
0#
#400000
b0 "
b0 ,
b0 4
07
b101000000 -
b101000000 .
b101000000 2
b1000101 +
b1000101 /
b1000101 3
1#
#404000
b101001 $
b101001 )
b101001 1
b101001 (
#405000
bx0010100100101000001001110010011000100101001001000010001100100010001000010010000000011111000111100001110100011100000110110001101000011001000110000001011100010110000101010001010000010011000100100001000100010000000011110000111000001101000011000000101100001010000010010000100000000111000001100000010100000100000000110000001000000001 5
0#
#410000
b10 "
b10 ,
b10 4
17
b1001000 +
b1001000 /
b1001000 3
b101001000 -
b101001000 .
b101001000 2
1#
#414000
b101010 $
b101010 )
b101010 1
b101010 (
#415000
bx001010100010100100101000001001110010011000100101001001000010001100100010001000010010000000011111000111100001110100011100000110110001101000011001000110000001011100010110000101010001010000010011000100100001000100010000000011110000111000001101000011000000101100001010000010010000100000000111000001100000010100000100000000110000001000000001 5
0#
#420000
07
b1 "
b1 ,
b1 4
16
b101010000 -
b101010000 .
b101010000 2
b1001011 +
b1001011 /
b1001011 3
1#
#424000
b101011 $
b101011 )
b101011 1
b101011 (
#425000
bx00101011001010100010100100101000001001110010011000100101001001000010001100100010001000010010000000011111000111100001110100011100000110110001101000011001000110000001011100010110000101010001010000010011000100100001000100010000000011110000111000001101000011000000101100001010000010010000100000000111000001100000010100000100000000110000001000000001 5
0#
#430000
18
b100 "
b100 ,
b100 4
06
b1001110 +
b1001110 /
b1001110 3
b101011000 -
b101011000 .
b101011000 2
1#
#434000
b101100 $
b101100 )
b101100 1
b101100 (
#435000
bx0010110000101011001010100010100100101000001001110010011000100101001001000010001100100010001000010010000000011111000111100001110100011100000110110001101000011001000110000001011100010110000101010001010000010011000100100001000100010000000011110000111000001101000011000000101100001010000010010000100000000111000001100000010100000100000000110000001000000001 5
0#
#440000
b101 "
b101 ,
b101 4
16
b101100000 -
b101100000 .
b101100000 2
b1010001 +
b1010001 /
b1010001 3
1#
#444000
b101101 $
b101101 )
b101101 1
b101101 (
#445000
bx001011010010110000101011001010100010100100101000001001110010011000100101001001000010001100100010001000010010000000011111000111100001110100011100000110110001101000011001000110000001011100010110000101010001010000010011000100100001000100010000000011110000111000001101000011000000101100001010000010010000100000000111000001100000010100000100000000110000001000000001 5
0#
#450000
08
b0 "
b0 ,
b0 4
06
b1010100 +
b1010100 /
b1010100 3
b101101000 -
b101101000 .
b101101000 2
1#
#454000
b101110 $
b101110 )
b101110 1
b101110 (
#455000
bx00101110001011010010110000101011001010100010100100101000001001110010011000100101001001000010001100100010001000010010000000011111000111100001110100011100000110110001101000011001000110000001011100010110000101010001010000010011000100100001000100010000000011110000111000001101000011000000101100001010000010010000100000000111000001100000010100000100000000110000001000000001 5
0#
#460000
b101110000 -
b101110000 .
b101110000 2
b1010111 +
b1010111 /
b1010111 3
1#
#464000
b101111 $
b101111 )
b101111 1
b101111 (
#465000
bx0010111100101110001011010010110000101011001010100010100100101000001001110010011000100101001001000010001100100010001000010010000000011111000111100001110100011100000110110001101000011001000110000001011100010110000101010001010000010011000100100001000100010000000011110000111000001101000011000000101100001010000010010000100000000111000001100000010100000100000000110000001000000001 5
0#
#470000
17
b11 "
b11 ,
b11 4
16
b1011010 +
b1011010 /
b1011010 3
b101111000 -
b101111000 .
b101111000 2
1#
#474000
b110000 $
b110000 )
b110000 1
b110000 (
#475000
bx001100000010111100101110001011010010110000101011001010100010100100101000001001110010011000100101001001000010001100100010001000010010000000011111000111100001110100011100000110110001101000011001000110000001011100010110000101010001010000010011000100100001000100010000000011110000111000001101000011000000101100001010000010010000100000000111000001100000010100000100000000110000001000000001 5
0#
#480000
07
b0 "
b0 ,
b0 4
06
b110000000 -
b110000000 .
b110000000 2
b1011101 +
b1011101 /
b1011101 3
1#
#484000
b110001 $
b110001 )
b110001 1
b110001 (
#485000
bx00110001001100000010111100101110001011010010110000101011001010100010100100101000001001110010011000100101001001000010001100100010001000010010000000011111000111100001110100011100000110110001101000011001000110000001011100010110000101010001010000010011000100100001000100010000000011110000111000001101000011000000101100001010000010010000100000000111000001100000010100000100000000110000001000000001 5
0#
#490000
18
b101 "
b101 ,
b101 4
16
b1100000 +
b1100000 /
b1100000 3
b110001000 -
b110001000 .
b110001000 2
1#
#494000
b110010 $
b110010 )
b110010 1
b110010 (
#495000
bx0011001000110001001100000010111100101110001011010010110000101011001010100010100100101000001001110010011000100101001001000010001100100010001000010010000000011111000111100001110100011100000110110001101000011001000110000001011100010110000101010001010000010011000100100001000100010000000011110000111000001101000011000000101100001010000010010000100000000111000001100000010100000100000000110000001000000001 5
0#
#500000
b1 "
b1 ,
b1 4
08
b110010000 -
b110010000 .
b110010000 2
b1100011 +
b1100011 /
b1100011 3
1#
#504000
b110011 $
b110011 )
b110011 1
b110011 (
#505000
bx001100110011001000110001001100000010111100101110001011010010110000101011001010100010100100101000001001110010011000100101001001000010001100100010001000010010000000011111000111100001110100011100000110110001101000011001000110000001011100010110000101010001010000010011000100100001000100010000000011110000111000001101000011000000101100001010000010010000100000000111000001100000010100000100000000110000001000000001 5
0#
#510000
b0 "
b0 ,
b0 4
06
b1100110 +
b1100110 /
b1100110 3
b110011000 -
b110011000 .
b110011000 2
1#
#514000
b110100 $
b110100 )
b110100 1
b110100 (
#515000
bx00110100001100110011001000110001001100000010111100101110001011010010110000101011001010100010100100101000001001110010011000100101001001000010001100100010001000010010000000011111000111100001110100011100000110110001101000011001000110000001011100010110000101010001010000010011000100100001000100010000000011110000111000001101000011000000101100001010000010010000100000000111000001100000010100000100000000110000001000000001 5
0#
#520000
18
17
b111 "
b111 ,
b111 4
16
b110100000 -
b110100000 .
b110100000 2
b1101001 +
b1101001 /
b1101001 3
1#
#524000
b110101 $
b110101 )
b110101 1
b110101 (
#525000
bx0011010100110100001100110011001000110001001100000010111100101110001011010010110000101011001010100010100100101000001001110010011000100101001001000010001100100010001000010010000000011111000111100001110100011100000110110001101000011001000110000001011100010110000101010001010000010011000100100001000100010000000011110000111000001101000011000000101100001010000010010000100000000111000001100000010100000100000000110000001000000001 5
0#
#530000
08
07
b0 "
b0 ,
b0 4
06
b1101100 +
b1101100 /
b1101100 3
b110101000 -
b110101000 .
b110101000 2
1#
#534000
b110110 $
b110110 )
b110110 1
b110110 (
#535000
bx001101100011010100110100001100110011001000110001001100000010111100101110001011010010110000101011001010100010100100101000001001110010011000100101001001000010001100100010001000010010000000011111000111100001110100011100000110110001101000011001000110000001011100010110000101010001010000010011000100100001000100010000000011110000111000001101000011000000101100001010000010010000100000000111000001100000010100000100000000110000001000000001 5
0#
#540000
18
b110 "
b110 ,
b110 4
17
b110110000 -
b110110000 .
b110110000 2
b1101111 +
b1101111 /
b1101111 3
1#
#544000
b110111 $
b110111 )
b110111 1
b110111 (
#545000
bx00110111001101100011010100110100001100110011001000110001001100000010111100101110001011010010110000101011001010100010100100101000001001110010011000100101001001000010001100100010001000010010000000011111000111100001110100011100000110110001101000011001000110000001011100010110000101010001010000010011000100100001000100010000000011110000111000001101000011000000101100001010000010010000100000000111000001100000010100000100000000110000001000000001 5
0#
#550000
08
b11 "
b11 ,
b11 4
16
b1110010 +
b1110010 /
b1110010 3
b110111000 -
b110111000 .
b110111000 2
1#
#554000
b111000 $
b111000 )
b111000 1
b111000 (
#555000
bx0011100000110111001101100011010100110100001100110011001000110001001100000010111100101110001011010010110000101011001010100010100100101000001001110010011000100101001001000010001100100010001000010010000000011111000111100001110100011100000110110001101000011001000110000001011100010110000101010001010000010011000100100001000100010000000011110000111000001101000011000000101100001010000010010000100000000111000001100000010100000100000000110000001000000001 5
0#
#560000
07
b0 "
b0 ,
b0 4
06
b111000000 -
b111000000 .
b111000000 2
b1110101 +
b1110101 /
b1110101 3
1#
#564000
b111001 $
b111001 )
b111001 1
b111001 (
#565000
bx001110010011100000110111001101100011010100110100001100110011001000110001001100000010111100101110001011010010110000101011001010100010100100101000001001110010011000100101001001000010001100100010001000010010000000011111000111100001110100011100000110110001101000011001000110000001011100010110000101010001010000010011000100100001000100010000000011110000111000001101000011000000101100001010000010010000100000000111000001100000010100000100000000110000001000000001 5
0#
#570000
b1111000 +
b1111000 /
b1111000 3
b111001000 -
b111001000 .
b111001000 2
1#
#574000
b111010 $
b111010 )
b111010 1
b111010 (
#575000
bx00111010001110010011100000110111001101100011010100110100001100110011001000110001001100000010111100101110001011010010110000101011001010100010100100101000001001110010011000100101001001000010001100100010001000010010000000011111000111100001110100011100000110110001101000011001000110000001011100010110000101010001010000010011000100100001000100010000000011110000111000001101000011000000101100001010000010010000100000000111000001100000010100000100000000110000001000000001 5
0#
#580000
b10 "
b10 ,
b10 4
17
b111010000 -
b111010000 .
b111010000 2
b1111011 +
b1111011 /
b1111011 3
1#
#584000
b111011 $
b111011 )
b111011 1
b111011 (
#585000
bx0011101100111010001110010011100000110111001101100011010100110100001100110011001000110001001100000010111100101110001011010010110000101011001010100010100100101000001001110010011000100101001001000010001100100010001000010010000000011111000111100001110100011100000110110001101000011001000110000001011100010110000101010001010000010011000100100001000100010000000011110000111000001101000011000000101100001010000010010000100000000111000001100000010100000100000000110000001000000001 5
0#
#590000
18
b100 "
b100 ,
b100 4
07
b1111110 +
b1111110 /
b1111110 3
b111011000 -
b111011000 .
b111011000 2
1#
#594000
b111100 $
b111100 )
b111100 1
b111100 (
#595000
bx001111000011101100111010001110010011100000110111001101100011010100110100001100110011001000110001001100000010111100101110001011010010110000101011001010100010100100101000001001110010011000100101001001000010001100100010001000010010000000011111000111100001110100011100000110110001101000011001000110000001011100010110000101010001010000010011000100100001000100010000000011110000111000001101000011000000101100001010000010010000100000000111000001100000010100000100000000110000001000000001 5
0#
#600000
b0 "
b0 ,
b0 4
08
b111100000 -
b111100000 .
b111100000 2
b10000001 +
b10000001 /
b10000001 3
1#
#604000
b111101 $
b111101 )
b111101 1
b111101 (
#605000
bx00111101001111000011101100111010001110010011100000110111001101100011010100110100001100110011001000110001001100000010111100101110001011010010110000101011001010100010100100101000001001110010011000100101001001000010001100100010001000010010000000011111000111100001110100011100000110110001101000011001000110000001011100010110000101010001010000010011000100100001000100010000000011110000111000001101000011000000101100001010000010010000100000000111000001100000010100000100000000110000001000000001 5
0#
#610000
b1 "
b1 ,
b1 4
16
b10000100 +
b10000100 /
b10000100 3
b111101000 -
b111101000 .
b111101000 2
1#
#614000
b111110 $
b111110 )
b111110 1
b111110 (
#615000
bx0011111000111101001111000011101100111010001110010011100000110111001101100011010100110100001100110011001000110001001100000010111100101110001011010010110000101011001010100010100100101000001001110010011000100101001001000010001100100010001000010010000000011111000111100001110100011100000110110001101000011001000110000001011100010110000101010001010000010011000100100001000100010000000011110000111000001101000011000000101100001010000010010000100000000111000001100000010100000100000000110000001000000001 5
0#
#620000
18
b100 "
b100 ,
b100 4
06
b111110000 -
b111110000 .
b111110000 2
b10000111 +
b10000111 /
b10000111 3
1#
#624000
b111111 $
b111111 )
b111111 1
b111111 (
#625000
bx001111110011111000111101001111000011101100111010001110010011100000110111001101100011010100110100001100110011001000110001001100000010111100101110001011010010110000101011001010100010100100101000001001110010011000100101001001000010001100100010001000010010000000011111000111100001110100011100000110110001101000011001000110000001011100010110000101010001010000010011000100100001000100010000000011110000111000001101000011000000101100001010000010010000100000000111000001100000010100000100000000110000001000000001 5
0#
#630000
b10001010 +
b10001010 /
b10001010 3
b111111000 -
b111111000 .
b111111000 2
1#
#634000
b1000000 $
b1000000 )
b1000000 1
b1000000 (
#635000
b1000000001111110011111000111101001111000011101100111010001110010011100000110111001101100011010100110100001100110011001000110001001100000010111100101110001011010010110000101011001010100010100100101000001001110010011000100101001001000010001100100010001000010010000000011111000111100001110100011100000110110001101000011001000110000001011100010110000101010001010000010011000100100001000100010000000011110000111000001101000011000000101100001010000010010000100000000111000001100000010100000100000000110000001000000001 5
0#
#640000
b0 "
b0 ,
b0 4
08
b0 -
b0 .
b0 2
b10001101 +
b10001101 /
b10001101 3
1#
#644000
b0 $
b0 )
b0 1
b1 (
#645000
b1000000001111110011111000111101001111000011101100111010001110010011100000110111001101100011010100110100001100110011001000110001001100000010111100101110001011010010110000101011001010100010100100101000001001110010011000100101001001000010001100100010001000010010000000011111000111100001110100011100000110110001101000011001000110000001011100010110000101010001010000010011000100100001000100010000000011110000111000001101000011000000101100001010000010010000100000000111000001100000010100000100000000110000001000000000 5
0#
#650000
17
b11 "
b11 ,
b11 4
16
b10010000 +
b10010000 /
b10010000 3
b1000 -
b1000 .
b1000 2
1#
#654000
b10 $
b10 )
b10 1
b10 (
#655000
0#
#660000
b10 "
b10 ,
b10 4
06
b10000 -
b10000 .
b10000 2
b10010011 +
b10010011 /
b10010011 3
1#
#664000
b11 $
b11 )
b11 1
b11 (
#665000
0#
#670000
b0 "
b0 ,
b0 4
07
b10010110 +
b10010110 /
b10010110 3
b11000 -
b11000 .
b11000 2
1#
#674000
b100 $
b100 )
b100 1
b100 (
#675000
0#
