64x8mem/cache.v
module    cache(  input                                  cache_adr,
                  input                  [23:0]          cache,
						output                 [2:0]           Out);
                        reg                    [2:0]           iner_out;
						always@(cache or cache_adr)
						         begin               
									                              iner_out [0] = cache [cache_adr];
																  iner_out [1] = cache [cache_adr+1];
																  iner_out [2] = cache [cache_adr+2];
							      end
                  assign                                  Out = iner_out;
endmodule

64x8mem/counter.v
module     counter(      input                           start,
                         input                           Clk,
						 input                           Rst,
						 input                           fin,
						 output                          cache_adr,
						 output                          forward);
						 
						 reg                 [2:0]       counter = 0;
						 reg                             rideon;
                         reg                             iner_fw;
                         assign                          forward = iner_fw;
						 always        @                (*)
						      begin
								   if                     (Rst == 0)
									                        rideon = 0;
									else
									   if                  (fin == 1 && counter == 2)
										                    rideon = 0;
									else								
						            if                  (start == 1)
									                        rideon = 1;
										else                 rideon = rideon;
						      end
						 always     @                   (Clk)
						      begin
								   if                     (rideon == 1)
						            if                  (counter == 7)
										      begin
										                       counter = 0;
												               iner_fw = 1;
												end
										else  begin          counter = counter+1;
										                     iner_fw = 0;
                                    end
								end
						 assign                          cache_adr = 3*counter;
endmodule

64x8mem/store.v
module store(    input                         wr,
                 input         [7:0]           DB,
				 input         [5:0]           AB,
				 input                         Clk,
				 input		                   Rst,
				 input                         forward,
				 input                         start,
			     output reg    [23:0]          cache,
				 output reg                    fin);
			  
			    reg            [7:0]           mem     [65:0];
			    reg            [5:0]           rd_mem_adr ;
                integer                        i;

			    always@(rd_mem_adr)
				    begin
						if          (!Rst)
						             fin = 0;
						else			 
                            if      (rd_mem_adr == 63)
									 fin = 1;
							else     fin = 0;
				    end

                always           @            (wr or Rst or forward or DB)
			            begin
			                  if              (Rst == 0)
			                        for(i = 0; i == 65; i = i+1) 
			                            begin           
			                                mem [i]= 8'b00000000;
					                    end //清空寄存器
			                  else
                               if             (wr == 0)
                                               mem [AB] [7:0] = DB [7:0];
										 else            mem [AB] [7:0] = DB [7:0];
						end

			always        @      (*)
			    begin
				    if        (start)
                           rd_mem_adr = 0;					 
					 else    if(forward == 1)
						         rd_mem_adr = rd_mem_adr+3;
								else rd_mem_adr = rd_mem_adr;
			    end
			  
            always        @      (rd_mem_adr or start)
			    begin
			                     cache [7:0]   <= mem [rd_mem_adr] ;
								 cache [15:8]  <= mem [rd_mem_adr+1];
								 cache [23:16] <= mem [rd_mem_adr+2];
			    end 
endmodule

64x8mem/top.v
module top (input                     start,
            input                     Rst,
            input                     Clk,
			input                     wr,
			input        [5:0]        AB,
            input        [7:0]        DB,
            output       [2:0]        Out);
            
            wire                      forward;
            wire         [23:0]       cache;
			wire                      cache_adr;
			wire                      fin;
				store mem(
				              .wr         (wr),
								  .DB         (DB),
								  .AB         (AB),
								  .Clk        (Clk),
								  .Rst        (Rst),
								  .start      (start),
								  .forward    (forward),
								  .cache      (cache),
								  .fin        (fin));
				counter counter1(
				                  .start      (start),
								  .Clk        (Clk),
								  .Rst        (Rst),
								  .fin        (fin),
								  .cache_adr  (cache_adr),
								  .forward    (forward));
				cache cache1(
				                  .cache_adr  (cache_adr),
								  .cache      (cache),
								  .Out        (Out));
endmodule

64x8mem/top_tb.v

`timescale 1ns/1ps

module tb_project (); /* this is automatically generated */

    // clock
    reg Clk;
    initial begin
        Clk = 1'b0;
        forever #(5) Clk = ~Clk;
    end

    // asynchronous reset
    reg Rst;
    initial begin
        Rst <= 1'b0;
        #1
        Rst <= 1'b1;
    end

    // (*NOTE*) replace reset, clock, others

    reg        start;
    reg [5: 0] AB;
    reg [7: 0] DB;
    reg        wr;
    wire [2: 0] out;
    integer idx1;

    top inst_project
        (
            .start (start),
            .Rst   (Rst),
            .Clk   (Clk),
            .AB    (AB),
            .DB    (DB),
            .wr    (wr),
            .Out   (out)
        );

    initial begin
        // do something
        AB    <= 0;
        DB    <= 0;
        start <= 0;
        wr    <= 0;
        repeat(2)@(posedge Clk);
        #2
        AB    <= 0;
        DB    <= 0;
        #9
        AB    <= 0;
        DB    <= 1;
        for (idx1 = 1; idx1 < 64; idx1 = idx1 + 1)
        begin
            #10
            AB <= idx1;
            DB <= idx1+1;
        end
        #9
        #2
        start  <= 1;
        #10
        start  <= 0;
        #8

        wr     <= 0;

        repeat(175)@(posedge Clk);
        $finish;
    end
integer i;
    initial
    	begin
      		$dumpfile("wave2.vcd"); 
            for(i=0;i<65;i=i+1)
                $dumpvars(0, tb_project,tb_project.inst_project.mem.mem[i]);

    	end



endmodule

64x8mem/wave.vcd
$date
	Sat Dec  5 19:36:40 2020
$end
$version
	Icarus Verilog
$end
$timescale
	1ps
$end
$scope module tb_project $end
$var wire 3 ! out [2:0] $end
$var reg 6 " AB [5:0] $end
$var reg 1 # Clk $end
$var reg 8 $ DB [7:0] $end
$var reg 1 % Rst $end
$var reg 1 & start $end
$var reg 1 ' wr $end
$var integer 32 ( i [31:0] $end
$var integer 32 ) idx1 [31:0] $end
$scope module inst_project $end
$var wire 6 * AB [5:0] $end
$var wire 1 # Clk $end
$var wire 8 + DB [7:0] $end
$var wire 1 % Rst $end
$var wire 1 & start $end
$var wire 1 ' wr $end
$var wire 1 , forward $end
$var wire 1 - fin $end
$var wire 1 . cache_adr $end
$var wire 24 / cache [23:0] $end
$var wire 3 0 Out [2:0] $end
$scope module cache1 $end
$var wire 3 1 Out [2:0] $end
$var wire 1 . cache_adr $end
$var wire 24 2 cache [23:0] $end
$var reg 3 3 iner_out [2:0] $end
$upscope $end
$scope module counter1 $end
$var wire 1 # Clk $end
$var wire 1 % Rst $end
$var wire 1 , forward $end
$var wire 1 & start $end
$var wire 1 - fin $end
$var wire 1 . cache_adr $end
$var reg 3 4 counter [2:0] $end
$var reg 1 5 iner_fw $end
$var reg 1 6 rideon $end
$upscope $end
$scope module mem $end
$var wire 6 7 AB [5:0] $end
$var wire 1 # Clk $end
$var wire 8 8 DB [7:0] $end
$var wire 1 % Rst $end
$var wire 1 , forward $end
$var wire 1 & start $end
$var wire 1 ' wr $end
$var reg 24 9 cache [23:0] $end
$var reg 1 - fin $end
$var reg 6 : rd_mem_adr [5:0] $end
$var integer 32 ; i [31:0] $end
$upscope $end
$upscope $end
$upscope $end
$scope module tb_project $end
$scope module inst_project $end
$scope module mem $end
$var reg 8 < \mem[0] [7:0] $end
$upscope $end
$upscope $end
$upscope $end
$scope module tb_project $end
$scope module inst_project $end
$scope module cache1 $end
$upscope $end
$scope module counter1 $end
$upscope $end
$scope module mem $end
$upscope $end
$upscope $end
$upscope $end
$scope module tb_project $end
$scope module inst_project $end
$scope module mem $end
$var reg 8 = \mem[1] [7:0] $end
$upscope $end
$upscope $end
$upscope $end
$scope module tb_project $end
$scope module inst_project $end
$scope module cache1 $end
$upscope $end
$scope module counter1 $end
$upscope $end
$scope module mem $end
$upscope $end
$upscope $end
$upscope $end
$scope module tb_project $end
$scope module inst_project $end
$scope module mem $end
$var reg 8 > \mem[2] [7:0] $end
$upscope $end
$upscope $end
$upscope $end
$scope module tb_project $end
$scope module inst_project $end
$scope module cache1 $end
$upscope $end
$scope module counter1 $end
$upscope $end
$scope module mem $end
$upscope $end
$upscope $end
$upscope $end
$scope module tb_project $end
$scope module inst_project $end
$scope module mem $end
$var reg 8 ? \mem[3] [7:0] $end
$upscope $end
$upscope $end
$upscope $end
$scope module tb_project $end
$scope module inst_project $end
$scope module cache1 $end
$upscope $end
$scope module counter1 $end
$upscope $end
$scope module mem $end
$upscope $end
$upscope $end
$upscope $end
$scope module tb_project $end
$scope module inst_project $end
$scope module mem $end
$var reg 8 @ \mem[4] [7:0] $end
$upscope $end
$upscope $end
$upscope $end
$scope module tb_project $end
$scope module inst_project $end
$scope module cache1 $end
$upscope $end
$scope module counter1 $end
$upscope $end
$scope module mem $end
$upscope $end
$upscope $end
$upscope $end
$scope module tb_project $end
$scope module inst_project $end
$scope module mem $end
$var reg 8 A \mem[5] [7:0] $end
$upscope $end
$upscope $end
$upscope $end
$scope module tb_project $end
$scope module inst_project $end
$scope module cache1 $end
$upscope $end
$scope module counter1 $end
$upscope $end
$scope module mem $end
$upscope $end
$upscope $end
$upscope $end
$scope module tb_project $end
$scope module inst_project $end
$scope module mem $end
$var reg 8 B \mem[6] [7:0] $end
$upscope $end
$upscope $end
$upscope $end
$scope module tb_project $end
$scope module inst_project $end
$scope module cache1 $end
$upscope $end
$scope module counter1 $end
$upscope $end
$scope module mem $end
$upscope $end
$upscope $end
$upscope $end
$scope module tb_project $end
$scope module inst_project $end
$scope module mem $end
$var reg 8 C \mem[7] [7:0] $end
$upscope $end
$upscope $end
$upscope $end
$scope module tb_project $end
$scope module inst_project $end
$scope module cache1 $end
$upscope $end
$scope module counter1 $end
$upscope $end
$scope module mem $end
$upscope $end
$upscope $end
$upscope $end
$scope module tb_project $end
$scope module inst_project $end
$scope module mem $end
$var reg 8 D \mem[8] [7:0] $end
$upscope $end
$upscope $end
$upscope $end
$scope module tb_project $end
$scope module inst_project $end
$scope module cache1 $end
$upscope $end
$scope module counter1 $end
$upscope $end
$scope module mem $end
$upscope $end
$upscope $end
$upscope $end
$scope module tb_project $end
$scope module inst_project $end
$scope module mem $end
$var reg 8 E \mem[9] [7:0] $end
$upscope $end
$upscope $end
$upscope $end
$scope module tb_project $end
$scope module inst_project $end
$scope module cache1 $end
$upscope $end
$scope module counter1 $end
$upscope $end
$scope module mem $end
$upscope $end
$upscope $end
$upscope $end
$scope module tb_project $end
$scope module inst_project $end
$scope module mem $end
$var reg 8 F \mem[10] [7:0] $end
$upscope $end
$upscope $end
$upscope $end
$scope module tb_project $end
$scope module inst_project $end
$scope module cache1 $end
$upscope $end
$scope module counter1 $end
$upscope $end
$scope module mem $end
$upscope $end
$upscope $end
$upscope $end
$scope module tb_project $end
$scope module inst_project $end
$scope module mem $end
$var reg 8 G \mem[11] [7:0] $end
$upscope $end
$upscope $end
$upscope $end
$scope module tb_project $end
$scope module inst_project $end
$scope module cache1 $end
$upscope $end
$scope module counter1 $end
$upscope $end
$scope module mem $end
$upscope $end
$upscope $end
$upscope $end
$scope module tb_project $end
$scope module inst_project $end
$scope module mem $end
$var reg 8 H \mem[12] [7:0] $end
$upscope $end
$upscope $end
$upscope $end
$scope module tb_project $end
$scope module inst_project $end
$scope module cache1 $end
$upscope $end
$scope module counter1 $end
$upscope $end
$scope module mem $end
$upscope $end
$upscope $end
$upscope $end
$scope module tb_project $end
$scope module inst_project $end
$scope module mem $end
$var reg 8 I \mem[13] [7:0] $end
$upscope $end
$upscope $end
$upscope $end
$scope module tb_project $end
$scope module inst_project $end
$scope module cache1 $end
$upscope $end
$scope module counter1 $end
$upscope $end
$scope module mem $end
$upscope $end
$upscope $end
$upscope $end
$scope module tb_project $end
$scope module inst_project $end
$scope module mem $end
$var reg 8 J \mem[14] [7:0] $end
$upscope $end
$upscope $end
$upscope $end
$scope module tb_project $end
$scope module inst_project $end
$scope module cache1 $end
$upscope $end
$scope module counter1 $end
$upscope $end
$scope module mem $end
$upscope $end
$upscope $end
$upscope $end
$scope module tb_project $end
$scope module inst_project $end
$scope module mem $end
$var reg 8 K \mem[15] [7:0] $end
$upscope $end
$upscope $end
$upscope $end
$scope module tb_project $end
$scope module inst_project $end
$scope module cache1 $end
$upscope $end
$scope module counter1 $end
$upscope $end
$scope module mem $end
$upscope $end
$upscope $end
$upscope $end
$scope module tb_project $end
$scope module inst_project $end
$scope module mem $end
$var reg 8 L \mem[16] [7:0] $end
$upscope $end
$upscope $end
$upscope $end
$scope module tb_project $end
$scope module inst_project $end
$scope module cache1 $end
$upscope $end
$scope module counter1 $end
$upscope $end
$scope module mem $end
$upscope $end
$upscope $end
$upscope $end
$scope module tb_project $end
$scope module inst_project $end
$scope module mem $end
$var reg 8 M \mem[17] [7:0] $end
$upscope $end
$upscope $end
$upscope $end
$scope module tb_project $end
$scope module inst_project $end
$scope module cache1 $end
$upscope $end
$scope module counter1 $end
$upscope $end
$scope module mem $end
$upscope $end
$upscope $end
$upscope $end
$scope module tb_project $end
$scope module inst_project $end
$scope module mem $end
$var reg 8 N \mem[18] [7:0] $end
$upscope $end
$upscope $end
$upscope $end
$scope module tb_project $end
$scope module inst_project $end
$scope module cache1 $end
$upscope $end
$scope module counter1 $end
$upscope $end
$scope module mem $end
$upscope $end
$upscope $end
$upscope $end
$scope module tb_project $end
$scope module inst_project $end
$scope module mem $end
$var reg 8 O \mem[19] [7:0] $end
$upscope $end
$upscope $end
$upscope $end
$scope module tb_project $end
$scope module inst_project $end
$scope module cache1 $end
$upscope $end
$scope module counter1 $end
$upscope $end
$scope module mem $end
$upscope $end
$upscope $end
$upscope $end
$scope module tb_project $end
$scope module inst_project $end
$scope module mem $end
$var reg 8 P \mem[20] [7:0] $end
$upscope $end
$upscope $end
$upscope $end
$scope module tb_project $end
$scope module inst_project $end
$scope module cache1 $end
$upscope $end
$scope module counter1 $end
$upscope $end
$scope module mem $end
$upscope $end
$upscope $end
$upscope $end
$scope module tb_project $end
$scope module inst_project $end
$scope module mem $end
$var reg 8 Q \mem[21] [7:0] $end
$upscope $end
$upscope $end
$upscope $end
$scope module tb_project $end
$scope module inst_project $end
$scope module cache1 $end
$upscope $end
$scope module counter1 $end
$upscope $end
$scope module mem $end
$upscope $end
$upscope $end
$upscope $end
$scope module tb_project $end
$scope module inst_project $end
$scope module mem $end
$var reg 8 R \mem[22] [7:0] $end
$upscope $end
$upscope $end
$upscope $end
$scope module tb_project $end
$scope module inst_project $end
$scope module cache1 $end
$upscope $end
$scope module counter1 $end
$upscope $end
$scope module mem $end
$upscope $end
$upscope $end
$upscope $end
$scope module tb_project $end
$scope module inst_project $end
$scope module mem $end
$var reg 8 S \mem[23] [7:0] $end
$upscope $end
$upscope $end
$upscope $end
$scope module tb_project $end
$scope module inst_project $end
$scope module cache1 $end
$upscope $end
$scope module counter1 $end
$upscope $end
$scope module mem $end
$upscope $end
$upscope $end
$upscope $end
$scope module tb_project $end
$scope module inst_project $end
$scope module mem $end
$var reg 8 T \mem[24] [7:0] $end
$upscope $end
$upscope $end
$upscope $end
$scope module tb_project $end
$scope module inst_project $end
$scope module cache1 $end
$upscope $end
$scope module counter1 $end
$upscope $end
$scope module mem $end
$upscope $end
$upscope $end
$upscope $end
$scope module tb_project $end
$scope module inst_project $end
$scope module mem $end
$var reg 8 U \mem[25] [7:0] $end
$upscope $end
$upscope $end
$upscope $end
$scope module tb_project $end
$scope module inst_project $end
$scope module cache1 $end
$upscope $end
$scope module counter1 $end
$upscope $end
$scope module mem $end
$upscope $end
$upscope $end
$upscope $end
$scope module tb_project $end
$scope module inst_project $end
$scope module mem $end
$var reg 8 V \mem[26] [7:0] $end
$upscope $end
$upscope $end
$upscope $end
$scope module tb_project $end
$scope module inst_project $end
$scope module cache1 $end
$upscope $end
$scope module counter1 $end
$upscope $end
$scope module mem $end
$upscope $end
$upscope $end
$upscope $end
$scope module tb_project $end
$scope module inst_project $end
$scope module mem $end
$var reg 8 W \mem[27] [7:0] $end
$upscope $end
$upscope $end
$upscope $end
$scope module tb_project $end
$scope module inst_project $end
$scope module cache1 $end
$upscope $end
$scope module counter1 $end
$upscope $end
$scope module mem $end
$upscope $end
$upscope $end
$upscope $end
$scope module tb_project $end
$scope module inst_project $end
$scope module mem $end
$var reg 8 X \mem[28] [7:0] $end
$upscope $end
$upscope $end
$upscope $end
$scope module tb_project $end
$scope module inst_project $end
$scope module cache1 $end
$upscope $end
$scope module counter1 $end
$upscope $end
$scope module mem $end
$upscope $end
$upscope $end
$upscope $end
$scope module tb_project $end
$scope module inst_project $end
$scope module mem $end
$var reg 8 Y \mem[29] [7:0] $end
$upscope $end
$upscope $end
$upscope $end
$scope module tb_project $end
$scope module inst_project $end
$scope module cache1 $end
$upscope $end
$scope module counter1 $end
$upscope $end
$scope module mem $end
$upscope $end
$upscope $end
$upscope $end
$scope module tb_project $end
$scope module inst_project $end
$scope module mem $end
$var reg 8 Z \mem[30] [7:0] $end
$upscope $end
$upscope $end
$upscope $end
$scope module tb_project $end
$scope module inst_project $end
$scope module cache1 $end
$upscope $end
$scope module counter1 $end
$upscope $end
$scope module mem $end
$upscope $end
$upscope $end
$upscope $end
$scope module tb_project $end
$scope module inst_project $end
$scope module mem $end
$var reg 8 [ \mem[31] [7:0] $end
$upscope $end
$upscope $end
$upscope $end
$scope module tb_project $end
$scope module inst_project $end
$scope module cache1 $end
$upscope $end
$scope module counter1 $end
$upscope $end
$scope module mem $end
$upscope $end
$upscope $end
$upscope $end
$scope module tb_project $end
$scope module inst_project $end
$scope module mem $end
$var reg 8 \ \mem[32] [7:0] $end
$upscope $end
$upscope $end
$upscope $end
$scope module tb_project $end
$scope module inst_project $end
$scope module cache1 $end
$upscope $end
$scope module counter1 $end
$upscope $end
$scope module mem $end
$upscope $end
$upscope $end
$upscope $end
$scope module tb_project $end
$scope module inst_project $end
$scope module mem $end
$var reg 8 ] \mem[33] [7:0] $end
$upscope $end
$upscope $end
$upscope $end
$scope module tb_project $end
$scope module inst_project $end
$scope module cache1 $end
$upscope $end
$scope module counter1 $end
$upscope $end
$scope module mem $end
$upscope $end
$upscope $end
$upscope $end
$scope module tb_project $end
$scope module inst_project $end
$scope module mem $end
$var reg 8 ^ \mem[34] [7:0] $end
$upscope $end
$upscope $end
$upscope $end
$scope module tb_project $end
$scope module inst_project $end
$scope module cache1 $end
$upscope $end
$scope module counter1 $end
$upscope $end
$scope module mem $end
$upscope $end
$upscope $end
$upscope $end
$scope module tb_project $end
$scope module inst_project $end
$scope module mem $end
$var reg 8 _ \mem[35] [7:0] $end
$upscope $end
$upscope $end
$upscope $end
$scope module tb_project $end
$scope module inst_project $end
$scope module cache1 $end
$upscope $end
$scope module counter1 $end
$upscope $end
$scope module mem $end
$upscope $end
$upscope $end
$upscope $end
$scope module tb_project $end
$scope module inst_project $end
$scope module mem $end
$var reg 8 ` \mem[36] [7:0] $end
$upscope $end
$upscope $end
$upscope $end
$scope module tb_project $end
$scope module inst_project $end
$scope module cache1 $end
$upscope $end
$scope module counter1 $end
$upscope $end
$scope module mem $end
$upscope $end
$upscope $end
$upscope $end
$scope module tb_project $end
$scope module inst_project $end
$scope module mem $end
$var reg 8 a \mem[37] [7:0] $end
$upscope $end
$upscope $end
$upscope $end
$scope module tb_project $end
$scope module inst_project $end
$scope module cache1 $end
$upscope $end
$scope module counter1 $end
$upscope $end
$scope module mem $end
$upscope $end
$upscope $end
$upscope $end
$scope module tb_project $end
$scope module inst_project $end
$scope module mem $end
$var reg 8 b \mem[38] [7:0] $end
$upscope $end
$upscope $end
$upscope $end
$scope module tb_project $end
$scope module inst_project $end
$scope module cache1 $end
$upscope $end
$scope module counter1 $end
$upscope $end
$scope module mem $end
$upscope $end
$upscope $end
$upscope $end
$scope module tb_project $end
$scope module inst_project $end
$scope module mem $end
$var reg 8 c \mem[39] [7:0] $end
$upscope $end
$upscope $end
$upscope $end
$scope module tb_project $end
$scope module inst_project $end
$scope module cache1 $end
$upscope $end
$scope module counter1 $end
$upscope $end
$scope module mem $end
$upscope $end
$upscope $end
$upscope $end
$scope module tb_project $end
$scope module inst_project $end
$scope module mem $end
$var reg 8 d \mem[40] [7:0] $end
$upscope $end
$upscope $end
$upscope $end
$scope module tb_project $end
$scope module inst_project $end
$scope module cache1 $end
$upscope $end
$scope module counter1 $end
$upscope $end
$scope module mem $end
$upscope $end
$upscope $end
$upscope $end
$scope module tb_project $end
$scope module inst_project $end
$scope module mem $end
$var reg 8 e \mem[41] [7:0] $end
$upscope $end
$upscope $end
$upscope $end
$scope module tb_project $end
$scope module inst_project $end
$scope module cache1 $end
$upscope $end
$scope module counter1 $end
$upscope $end
$scope module mem $end
$upscope $end
$upscope $end
$upscope $end
$scope module tb_project $end
$scope module inst_project $end
$scope module mem $end
$var reg 8 f \mem[42] [7:0] $end
$upscope $end
$upscope $end
$upscope $end
$scope module tb_project $end
$scope module inst_project $end
$scope module cache1 $end
$upscope $end
$scope module counter1 $end
$upscope $end
$scope module mem $end
$upscope $end
$upscope $end
$upscope $end
$scope module tb_project $end
$scope module inst_project $end
$scope module mem $end
$var reg 8 g \mem[43] [7:0] $end
$upscope $end
$upscope $end
$upscope $end
$scope module tb_project $end
$scope module inst_project $end
$scope module cache1 $end
$upscope $end
$scope module counter1 $end
$upscope $end
$scope module mem $end
$upscope $end
$upscope $end
$upscope $end
$scope module tb_project $end
$scope module inst_project $end
$scope module mem $end
$var reg 8 h \mem[44] [7:0] $end
$upscope $end
$upscope $end
$upscope $end
$scope module tb_project $end
$scope module inst_project $end
$scope module cache1 $end
$upscope $end
$scope module counter1 $end
$upscope $end
$scope module mem $end
$upscope $end
$upscope $end
$upscope $end
$scope module tb_project $end
$scope module inst_project $end
$scope module mem $end
$var reg 8 i \mem[45] [7:0] $end
$upscope $end
$upscope $end
$upscope $end
$scope module tb_project $end
$scope module inst_project $end
$scope module cache1 $end
$upscope $end
$scope module counter1 $end
$upscope $end
$scope module mem $end
$upscope $end
$upscope $end
$upscope $end
$scope module tb_project $end
$scope module inst_project $end
$scope module mem $end
$var reg 8 j \mem[46] [7:0] $end
$upscope $end
$upscope $end
$upscope $end
$scope module tb_project $end
$scope module inst_project $end
$scope module cache1 $end
$upscope $end
$scope module counter1 $end
$upscope $end
$scope module mem $end
$upscope $end
$upscope $end
$upscope $end
$scope module tb_project $end
$scope module inst_project $end
$scope module mem $end
$var reg 8 k \mem[47] [7:0] $end
$upscope $end
$upscope $end
$upscope $end
$scope module tb_project $end
$scope module inst_project $end
$scope module cache1 $end
$upscope $end
$scope module counter1 $end
$upscope $end
$scope module mem $end
$upscope $end
$upscope $end
$upscope $end
$scope module tb_project $end
$scope module inst_project $end
$scope module mem $end
$var reg 8 l \mem[48] [7:0] $end
$upscope $end
$upscope $end
$upscope $end
$scope module tb_project $end
$scope module inst_project $end
$scope module cache1 $end
$upscope $end
$scope module counter1 $end
$upscope $end
$scope module mem $end
$upscope $end
$upscope $end
$upscope $end
$scope module tb_project $end
$scope module inst_project $end
$scope module mem $end
$var reg 8 m \mem[49] [7:0] $end
$upscope $end
$upscope $end
$upscope $end
$scope module tb_project $end
$scope module inst_project $end
$scope module cache1 $end
$upscope $end
$scope module counter1 $end
$upscope $end
$scope module mem $end
$upscope $end
$upscope $end
$upscope $end
$scope module tb_project $end
$scope module inst_project $end
$scope module mem $end
$var reg 8 n \mem[50] [7:0] $end
$upscope $end
$upscope $end
$upscope $end
$scope module tb_project $end
$scope module inst_project $end
$scope module cache1 $end
$upscope $end
$scope module counter1 $end
$upscope $end
$scope module mem $end
$upscope $end
$upscope $end
$upscope $end
$scope module tb_project $end
$scope module inst_project $end
$scope module mem $end
$var reg 8 o \mem[51] [7:0] $end
$upscope $end
$upscope $end
$upscope $end
$scope module tb_project $end
$scope module inst_project $end
$scope module cache1 $end
$upscope $end
$scope module counter1 $end
$upscope $end
$scope module mem $end
$upscope $end
$upscope $end
$upscope $end
$scope module tb_project $end
$scope module inst_project $end
$scope module mem $end
$var reg 8 p \mem[52] [7:0] $end
$upscope $end
$upscope $end
$upscope $end
$scope module tb_project $end
$scope module inst_project $end
$scope module cache1 $end
$upscope $end
$scope module counter1 $end
$upscope $end
$scope module mem $end
$upscope $end
$upscope $end
$upscope $end
$scope module tb_project $end
$scope module inst_project $end
$scope module mem $end
$var reg 8 q \mem[53] [7:0] $end
$upscope $end
$upscope $end
$upscope $end
$scope module tb_project $end
$scope module inst_project $end
$scope module cache1 $end
$upscope $end
$scope module counter1 $end
$upscope $end
$scope module mem $end
$upscope $end
$upscope $end
$upscope $end
$scope module tb_project $end
$scope module inst_project $end
$scope module mem $end
$var reg 8 r \mem[54] [7:0] $end
$upscope $end
$upscope $end
$upscope $end
$scope module tb_project $end
$scope module inst_project $end
$scope module cache1 $end
$upscope $end
$scope module counter1 $end
$upscope $end
$scope module mem $end
$upscope $end
$upscope $end
$upscope $end
$scope module tb_project $end
$scope module inst_project $end
$scope module mem $end
$var reg 8 s \mem[55] [7:0] $end
$upscope $end
$upscope $end
$upscope $end
$scope module tb_project $end
$scope module inst_project $end
$scope module cache1 $end
$upscope $end
$scope module counter1 $end
$upscope $end
$scope module mem $end
$upscope $end
$upscope $end
$upscope $end
$scope module tb_project $end
$scope module inst_project $end
$scope module mem $end
$var reg 8 t \mem[56] [7:0] $end
$upscope $end
$upscope $end
$upscope $end
$scope module tb_project $end
$scope module inst_project $end
$scope module cache1 $end
$upscope $end
$scope module counter1 $end
$upscope $end
$scope module mem $end
$upscope $end
$upscope $end
$upscope $end
$scope module tb_project $end
$scope module inst_project $end
$scope module mem $end
$var reg 8 u \mem[57] [7:0] $end
$upscope $end
$upscope $end
$upscope $end
$scope module tb_project $end
$scope module inst_project $end
$scope module cache1 $end
$upscope $end
$scope module counter1 $end
$upscope $end
$scope module mem $end
$upscope $end
$upscope $end
$upscope $end
$scope module tb_project $end
$scope module inst_project $end
$scope module mem $end
$var reg 8 v \mem[58] [7:0] $end
$upscope $end
$upscope $end
$upscope $end
$scope module tb_project $end
$scope module inst_project $end
$scope module cache1 $end
$upscope $end
$scope module counter1 $end
$upscope $end
$scope module mem $end
$upscope $end
$upscope $end
$upscope $end
$scope module tb_project $end
$scope module inst_project $end
$scope module mem $end
$var reg 8 w \mem[59] [7:0] $end
$upscope $end
$upscope $end
$upscope $end
$scope module tb_project $end
$scope module inst_project $end
$scope module cache1 $end
$upscope $end
$scope module counter1 $end
$upscope $end
$scope module mem $end
$upscope $end
$upscope $end
$upscope $end
$scope module tb_project $end
$scope module inst_project $end
$scope module mem $end
$var reg 8 x \mem[60] [7:0] $end
$upscope $end
$upscope $end
$upscope $end
$scope module tb_project $end
$scope module inst_project $end
$scope module cache1 $end
$upscope $end
$scope module counter1 $end
$upscope $end
$scope module mem $end
$upscope $end
$upscope $end
$upscope $end
$scope module tb_project $end
$scope module inst_project $end
$scope module mem $end
$var reg 8 y \mem[61] [7:0] $end
$upscope $end
$upscope $end
$upscope $end
$scope module tb_project $end
$scope module inst_project $end
$scope module cache1 $end
$upscope $end
$scope module counter1 $end
$upscope $end
$scope module mem $end
$upscope $end
$upscope $end
$upscope $end
$scope module tb_project $end
$scope module inst_project $end
$scope module mem $end
$var reg 8 z \mem[62] [7:0] $end
$upscope $end
$upscope $end
$upscope $end
$scope module tb_project $end
$scope module inst_project $end
$scope module cache1 $end
$upscope $end
$scope module counter1 $end
$upscope $end
$scope module mem $end
$upscope $end
$upscope $end
$upscope $end
$scope module tb_project $end
$scope module inst_project $end
$scope module mem $end
$var reg 8 { \mem[63] [7:0] $end
$upscope $end
$upscope $end
$upscope $end
$scope module tb_project $end
$scope module inst_project $end
$scope module cache1 $end
$upscope $end
$scope module counter1 $end
$upscope $end
$scope module mem $end
$upscope $end
$upscope $end
$upscope $end
$scope module tb_project $end
$scope module inst_project $end
$scope module mem $end
$var reg 8 | \mem[64] [7:0] $end
$upscope $end
$upscope $end
$upscope $end
$enddefinitions $end
#0
$dumpvars
bx |
bx {
bx z
bx y
bx x
bx w
bx v
bx u
bx t
bx s
bx r
bx q
bx p
bx o
bx n
bx m
bx l
bx k
bx j
bx i
bx h
bx g
bx f
bx e
bx d
bx c
bx b
bx a
bx `
bx _
bx ^
bx ]
bx \
bx [
bx Z
bx Y
bx X
bx W
bx V
bx U
bx T
bx S
bx R
bx Q
bx P
bx O
bx N
bx M
bx L
bx K
bx J
bx I
bx H
bx G
bx F
bx E
bx D
bx C
bx B
bx A
bx @
bx ?
bx >
bx =
bx <
b0 ;
b0 :
bx 9
b0 8
b0 7
06
x5
b0 4
bx 3
bx 2
bx 1
bx 0
bx /
0.
0-
x,
b0 +
b0 *
bx )
b1000001 (
0'
0&
0%
b0 $
0#
b0 "
bx !
$end
#1000
b0 <
1%
#5000
1#
#10000
0#
#15000
1#
#20000
0#
#25000
1#
#26000
b1 <
b1 $
b1 +
b1 8
b1 )
#30000
0#
#35000
1#
#36000
b10 =
b10 $
b10 +
b10 8
b1 "
b1 *
b1 7
b10 )
#40000
0#
#45000
1#
#46000
b11 >
b11 $
b11 +
b11 8
b10 "
b10 *
b10 7
b11 )
#50000
0#
#55000
1#
#56000
b100 ?
b100 $
b100 +
b100 8
b11 "
b11 *
b11 7
b100 )
#60000
0#
#65000
1#
#66000
b101 @
b101 $
b101 +
b101 8
b100 "
b100 *
b100 7
b101 )
#70000
0#
#75000
1#
#76000
b110 A
b110 $
b110 +
b110 8
b101 "
b101 *
b101 7
b110 )
#80000
0#
#85000
1#
#86000
b111 B
b111 $
b111 +
b111 8
b110 "
b110 *
b110 7
b111 )
#90000
0#
#95000
1#
#96000
b1000 C
b1000 $
b1000 +
b1000 8
b111 "
b111 *
b111 7
b1000 )
#100000
0#
#105000
1#
#106000
b1001 D
b1001 $
b1001 +
b1001 8
b1000 "
b1000 *
b1000 7
b1001 )
#110000
0#
#115000
1#
#116000
b1010 E
b1010 $
b1010 +
b1010 8
b1001 "
b1001 *
b1001 7
b1010 )
#120000
0#
#125000
1#
#126000
b1011 F
b1011 $
b1011 +
b1011 8
b1010 "
b1010 *
b1010 7
b1011 )
#130000
0#
#135000
1#
#136000
b1100 G
b1100 $
b1100 +
b1100 8
b1011 "
b1011 *
b1011 7
b1100 )
#140000
0#
#145000
1#
#146000
b1101 H
b1101 $
b1101 +
b1101 8
b1100 "
b1100 *
b1100 7
b1101 )
#150000
0#
#155000
1#
#156000
b1110 I
b1110 $
b1110 +
b1110 8
b1101 "
b1101 *
b1101 7
b1110 )
#160000
0#
#165000
1#
#166000
b1111 J
b1111 $
b1111 +
b1111 8
b1110 "
b1110 *
b1110 7
b1111 )
#170000
0#
#175000
1#
#176000
b10000 K
b10000 $
b10000 +
b10000 8
b1111 "
b1111 *
b1111 7
b10000 )
#180000
0#
#185000
1#
